README.rst
setup.py
huhu/__init__.py
huhu.egg-info/PKG-INFO
huhu.egg-info/SOURCES.txt
huhu.egg-info/dependency_links.txt
huhu.egg-info/entry_points.txt
huhu.egg-info/top_level.txt