Metadata-Version: 1.1
Name: huhu
Version: 0.0.5
Summary: An experimental script language for kids, written in Python
Home-page: https://github.com/mehmetkose/huhu
Author: Mehmet Kose
Author-email: mehmetkose122@gmail.com
License: MIT
Platform: UNKNOWN
Classifier: Environment :: Console
Classifier: Intended Audience :: Developers
Classifier: Intended Audience :: System Administrators
Classifier: Programming Language :: Python :: 3.4
Classifier: Programming Language :: Python :: 3.5
Classifier: Programming Language :: Python :: 3.6
Classifier: License :: OSI Approved :: MIT License
Classifier: Topic :: Software Development :: Build Tools
Classifier: Topic :: Software Development :: Libraries :: Python Modules
Provides: huhu
